graphs_akohl/__init__.py
graphs_akohl/heapq.py
graphs_akohl/sp.py
graphs_akohl-0.0.1.dist-info/METADATA
graphs_akohl-0.0.1.dist-info/WHEEL
graphs_akohl-0.0.1.dist-info/RECORD
