Metadata-Version: 2.3
Name: graphs_akohl
Version: 0.0.1
Summary: Dijkstra's Shortest Path Package
Project-URL: Homepage, https://github.com/pypa/sampleproject
Project-URL: Bug Tracker, https://github.com/pypa/sampleproject/issues
Author: Adam Kohl
Classifier: License :: OSI Approved :: MIT License
Classifier: Operating System :: OS Independent
Classifier: Programming Language :: Python :: 3
Requires-Python: >=3.7
